<?xml version="1.0"?>
<openerp>
    <data>
        
        <record model="ir.sequence.type" id="seq_type_emp_id1">
            <field name="name">TripManagement</field>
            <field name="code">trip.management</field>
        </record>

        <record model="ir.sequence" id="seq_emp_id1">
            <field name="name">Name</field>
            <field name="code">trip.management</field>
            <field name="prefix"></field>
            <field name="padding">3</field>
        </record>

        <record model="ir.sequence.type" id="seq_type_emp_id1">
            <field name="name">RouteManagement</field>
            <field name="code">route.management</field>
        </record>

        <record model="ir.sequence" id="seq_emp_id1">
            <field name="name">Name</field>
            <field name="code">route.management</field>
            <field name="prefix"></field>
            <field name="padding">3</field>
        </record>

    </data>
</openerp>